JaqalPaq_extras_dev-1.1.0b1.data/data/share/jaqalpaq/examples/Tutorials/Transpiler_Demo.ipynb
JaqalPaq_extras_dev-1.1.0b1.data/data/share/jaqalpaq/tests/test_smoke.py
JaqalPaq_extras_dev-1.1.0b1.data/data/share/jaqalpaq/tests/scheduler/__init__.py
JaqalPaq_extras_dev-1.1.0b1.data/data/share/jaqalpaq/tests/scheduler/test_scheduler.py
JaqalPaq_extras_dev-1.1.0b1.data/data/share/jaqalpaq/tests/transpilers/__init__.py
JaqalPaq_extras_dev-1.1.0b1.data/data/share/jaqalpaq/tests/transpilers/cirq/__init__.py
JaqalPaq_extras_dev-1.1.0b1.data/data/share/jaqalpaq/tests/transpilers/cirq/test_cirq_transpiler.py
JaqalPaq_extras_dev-1.1.0b1.data/data/share/jaqalpaq/tests/transpilers/projectq/__init__.py
JaqalPaq_extras_dev-1.1.0b1.data/data/share/jaqalpaq/tests/transpilers/projectq/test_projectq_transpiler.py
JaqalPaq_extras_dev-1.1.0b1.data/data/share/jaqalpaq/tests/transpilers/qiskit/__init__.py
JaqalPaq_extras_dev-1.1.0b1.data/data/share/jaqalpaq/tests/transpilers/qiskit/test_qiskit_backend.py
JaqalPaq_extras_dev-1.1.0b1.data/data/share/jaqalpaq/tests/transpilers/qiskit/test_qiskit_gates.py
JaqalPaq_extras_dev-1.1.0b1.data/data/share/jaqalpaq/tests/transpilers/qiskit/test_qiskit_reverse_transpiler.py
JaqalPaq_extras_dev-1.1.0b1.data/data/share/jaqalpaq/tests/transpilers/qiskit/test_qiskit_transpiler.py
JaqalPaq_extras_dev-1.1.0b1.data/data/share/jaqalpaq/tests/transpilers/qiskit/test_qiskit_unroller.py
JaqalPaq_extras_dev-1.1.0b1.data/data/share/jaqalpaq/tests/transpilers/quil/__init__.py
JaqalPaq_extras_dev-1.1.0b1.data/data/share/jaqalpaq/tests/transpilers/quil/test_quil.py
JaqalPaq_extras_dev-1.1.0b1.data/data/share/jaqalpaq/tests/transpilers/tket/__init__.py
JaqalPaq_extras_dev-1.1.0b1.data/data/share/jaqalpaq/tests/transpilers/tket/test_tket_backend.py
JaqalPaq_extras_dev-1.1.0b1.data/data/share/jaqalpaq/tests/transpilers/tket/test_tket_reverse_transpiler.py
JaqalPaq_extras_dev-1.1.0b1.data/data/share/jaqalpaq/tests/transpilers/tket/test_tket_transpiler.py
JaqalPaq_extras_dev-1.1.0b1.dist-info/LICENSE
JaqalPaq_extras_dev-1.1.0b1.dist-info/METADATA
JaqalPaq_extras_dev-1.1.0b1.dist-info/NOTICE
JaqalPaq_extras_dev-1.1.0b1.dist-info/WHEEL
JaqalPaq_extras_dev-1.1.0b1.dist-info/top_level.txt
JaqalPaq_extras_dev-1.1.0b1.dist-info/RECORD
