Metadata-Version: 2.1
Name: JaqalPaq-extras-dev
Version: 1.1.0b1
Summary: Python tools for Jaqal (extras)
Home-page: https://qscout.sandia.gov
Author: Benjamin C. A. Morrison, Jay Wesley Van Der Wall, Daniel Lobser, Antonio Russo, Kenneth Rudinger, Peter Maunz
Author-email: qscout@sandia.gov
License: Apache
Classifier: Development Status :: 4 - Beta
Classifier: Intended Audience :: Science/Research
Classifier: License :: OSI Approved :: Apache Software License
Classifier: Programming Language :: Python :: 3
Classifier: Topic :: Scientific/Engineering :: Physics
Classifier: Operating System :: Microsoft :: Windows
Classifier: Operating System :: MacOS :: MacOS X
Classifier: Operating System :: Unix
Requires-Python: >=3.6.5
License-File: LICENSE
License-File: NOTICE
Requires-Dist: JaqalPaq-dev (==1.1.0b1)
Requires-Dist: QSCOUT-gatemodels-dev (>=1.1.0b1)
Provides-Extra: cirq
Requires-Dist: cirq (<0.15.0,>=0.11.0) ; extra == 'cirq'
Provides-Extra: projectq
Requires-Dist: projectq (<0.8.0,>=0.5.1) ; extra == 'projectq'
Provides-Extra: pyquil
Requires-Dist: pyquil (<3.0.0,>=2.21.0) ; extra == 'pyquil'
Provides-Extra: pytket
Requires-Dist: pytket (<2.0.0,>=1.0.1) ; extra == 'pytket'
Provides-Extra: qiskit
Requires-Dist: qiskit (<0.37.0,>=0.27.0) ; extra == 'qiskit'
Provides-Extra: tests
Requires-Dist: pytest ; extra == 'tests'
Provides-Extra: tutorial
Requires-Dist: pytket-qiskit (==0.24.0) ; extra == 'tutorial'
Requires-Dist: qiskit-nature[pyscf] (==0.3.2) ; extra == 'tutorial'
